tortuga/__init__.py
tortuga-2.0.0.dist-info/METADATA
tortuga-2.0.0.dist-info/WHEEL
tortuga-2.0.0.dist-info/licenses/LICENSE.txt
tortuga-2.0.0.dist-info/RECORD
