Metadata-Version: 2.4
Name: tortuga
Version: 2.0.0
Summary: Una implementación multilingüe del módulo Turtle.py de Python. A multilingual implementation of Python's turtle.py module.
Project-URL: Homepage, https://github.com/asweigart/tortuga
Project-URL: Issues, https://github.com/asweigart/tortuga/issues
Author-email: Al Sweigart <al@inventwithpython.com>
License-Expression: PSF-2.0
License-File: LICENSE.txt
Classifier: Operating System :: OS Independent
Classifier: Programming Language :: Python :: 3
Requires-Python: >=2.7
